{
  "description": "Per-file counts of album/artist-derived identifiers (#303). scripts/terminology_ratchet.py --check fails CI when a generic module's count drifts; sanctioned AOTY surfaces are exempt.",
  "generic_total": 1908,
  "files": {
    "cli/commands.py": 2,
    "cli/main.py": 2,
    "cli/preflight_cmd.py": 1,
    "cli/run.py": 55,
    "cli/select_cmd.py": 1,
    "cli/stages.py": 1,
    "config/descriptor.py": 20,
    "config/gates.py": 4,
    "config/pipeline_yaml.py": 28,
    "data/cleaning.py": 27,
    "data/ingest.py": 13,
    "data/lineage.py": 20,
    "data/manifests.py": 19,
    "data/split.py": 60,
    "data/split_types.py": 5,
    "data/validation.py": 15,
    "evaluation/prior_predictive.py": 18,
    "evaluation/slices.py": 1,
    "features/__init__.py": 8,
    "features/album_type.py": 30,
    "features/artist.py": 18,
    "features/collaboration.py": 9,
    "features/genre.py": 1,
    "features/history.py": 6,
    "features/packs/aoty.py": 5,
    "features/registry.py": 9,
    "features/temporal.py": 16,
    "gpu_memory/calibration_store.py": 4,
    "gpu_memory/estimate.py": 19,
    "model_preflight.py": 32,
    "model_preflight_data.py": 11,
    "models/bayes/__init__.py": 3,
    "models/bayes/diagnostics.py": 2,
    "models/bayes/fit.py": 13,
    "models/bayes/likelihoods.py": 1,
    "models/bayes/model.py": 195,
    "models/bayes/predict.py": 70,
    "models/bayes/priors.py": 61,
    "models/bayes/rollout.py": 6,
    "pipelines/backtest.py": 1,
    "pipelines/build_features.py": 17,
    "pipelines/create_splits.py": 62,
    "pipelines/evaluate.py": 162,
    "pipelines/orchestrator.py": 99,
    "pipelines/predict_next.py": 217,
    "pipelines/prepare_dataset.py": 9,
    "pipelines/publication.py": 59,
    "pipelines/sensitivity.py": 34,
    "pipelines/stages.py": 36,
    "pipelines/train_bayes.py": 227,
    "pipelines/training_summary.py": 10,
    "preflight/cache.py": 10,
    "preflight/calibrate.py": 6,
    "preflight/check.py": 12,
    "preflight/full_check.py": 29,
    "preflight/mini_run.py": 22,
    "preflight/output.py": 3,
    "reporting/figures.py": 43,
    "reporting/model_card.py": 50,
    "reporting/tables.py": 2,
    "select/orchestrate.py": 7,
    "select/prior_screen.py": 11,
    "select/runner.py": 2,
    "select/space.py": 7,
    "utils/hashing.py": 1,
    "visualization/__init__.py": 4,
    "visualization/dashboard.py": 86
  }
}
